{
  "cookies": [
    {
      "name": "m",
      "value": "a4e0a5c1-6a3d-4816-bdfa-af54c28a93aff3bc8f",
      "domain": "m.stripe.com",
      "path": "/",
      "expires": 1732979514.60624,
      "httpOnly": true,
      "secure": true,
      "sameSite": "None"
    },
    {
      "name": "__stripe_mid",
      "value": "3504e319-badb-4780-989b-da9a084295d25f52d2",
      "domain": ".pulse-frontend.web.app",
      "path": "/",
      "expires": 1729955514,
      "httpOnly": false,
      "secure": true,
      "sameSite": "Strict"
    },
    {
      "name": "__stripe_sid",
      "value": "d62d6ccf-e03e-4854-8733-46fcbf155c424c1d84",
      "domain": ".pulse-frontend.web.app",
      "path": "/",
      "expires": 1698421314,
      "httpOnly": false,
      "secure": true,
      "sameSite": "Strict"
    }
  ],
  "origins": [
    {
      "origin": "https://pulse-frontend.web.app",
      "localStorage": [
        {
          "name": "tenant",
          "value": "{\"plan\":\"free\",\"planStatus\":\"active\",\"_id\":\"650856d147b8b57c22792848\",\"name\":\"default\",\"url\":\"default\",\"createdBy\":\"650856d147b8b54bb8792846\",\"updatedBy\":\"650856d147b8b54bb8792846\",\"createdAt\":\"2023-09-18T13:55:29.628Z\",\"updatedAt\":\"2023-09-18T13:55:29.628Z\",\"__v\":0,\"id\":\"650856d147b8b57c22792848\",\"settings\":{\"_id\":\"650856d147b8b5a04179284a\",\"theme\":\"default\",\"tenant\":\"650856d147b8b57c22792848\",\"createdBy\":\"650856d147b8b54bb8792846\",\"backgroundImages\":[],\"logos\":[],\"createdAt\":\"2023-09-18T13:55:29.762Z\",\"updatedAt\":\"2023-09-18T13:55:29.762Z\",\"__v\":0,\"id\":\"650856d147b8b5a04179284a\"}}"
        },
        {
          "name": "language",
          "value": "en"
        },
        {
          "name": "jwt",
          "value": "eyJhbGciOiJIUzI1NiIsInR5cCI6IkpXVCJ9.eyJpZCI6IjY1MGYwN2IwMzUxMGRiMGFjMjc3NzkyYyIsImlhdCI6MTY5ODQxOTUxNCwiZXhwIjoxNjk5MDI0MzE0fQ.mcpJSOOxooQ63BYRC3stikTkWXee4Y7S1C0oJ68rZPc"
        }
      ]
    }
  ]
}